sumap/__init__.py
sumap/helpers.py
sumap/sumap_.py
sumap-0.0.0.dev8.dist-info/LICENSE
sumap-0.0.0.dev8.dist-info/METADATA
sumap-0.0.0.dev8.dist-info/WHEEL
sumap-0.0.0.dev8.dist-info/top_level.txt
sumap-0.0.0.dev8.dist-info/RECORD
