Metadata-Version: 2.1
Name: sumap
Version: 0.0.0.dev8
Summary: SUMAP: Supervised UMAP
Home-page: https://github.com/tianlinhe/sumap
Author: Tianlin He
Author-email: tinaho_ok@hotmail.com
License: BSD 3-Clause License        
Platform: UNKNOWN
License-File: LICENSE
Requires-Dist: numpy (>=1.17)
Requires-Dist: scikit-learn (>=0.22)
Requires-Dist: pynndescent (>=0.5)
Requires-Dist: scipy (>=1.3.1)
Requires-Dist: numba (>=0.51.2)
Requires-Dist: tbb (>=2019.0)
Requires-Dist: umap-learn (>=0.5.1)
